{"status":"done","publicPath":"http://localhost:3000/assets/bundles/","chunks":{"main":[{"name":"main-11e811c7d97ac5e286c2.js","publicPath":"http://localhost:3000/assets/bundles/main-11e811c7d97ac5e286c2.js","path":"/home/dhiraj/iodide/server/static/bundles/main-11e811c7d97ac5e286c2.js"},{"name":"main.eb43bb010abb3752866a.hot-update.js","publicPath":"http://localhost:3000/assets/bundles/main.eb43bb010abb3752866a.hot-update.js","path":"/home/dhiraj/iodide/server/static/bundles/main.eb43bb010abb3752866a.hot-update.js"}]},"error":"ModuleBuildError","message":"Module build failed (from ./node_modules/babel-loader/lib/index.js):\nSyntaxError: JSX value should be either an expression or a quoted JSX text (28:26)\n\n  26 |             </a>\n  27 |             <div className='notebook-owner'>\n> 28 |               By: <a href=`/{notebook.owner}`>{notebook.owner}</a>\n     |                           ^\n  29 |             </div>\n  30 |           </div>\n  31 |         )\n"}